sponsorblock/__init__.py
sponsorblock/__main__.py
sponsorblock/client.py
sponsorblock/database.py
sponsorblock/errors.py
sponsorblock/models.py
sponsorblock/utils.py
sponsorblock.py-0.2.3.dist-info/LICENSE
sponsorblock.py-0.2.3.dist-info/METADATA
sponsorblock.py-0.2.3.dist-info/WHEEL
sponsorblock.py-0.2.3.dist-info/entry_points.txt
sponsorblock.py-0.2.3.dist-info/top_level.txt
sponsorblock.py-0.2.3.dist-info/RECORD
