Metadata-Version: 2.1
Name: sponsorblock.py
Version: 0.2.3
Summary: An unofficial wrapper for the SponsorBlock API
Home-page: https://wasi-master.github.io/sponsorblock.py/
Author: Wasi Master
Author-email: arianmollik323@gmail.com
License: MIT
Keywords: sponsorblock.py,documentation,sponsorblock,python,api,wrapper,sponsor,block,youtube,youtube-dl,youtube-dlp
Classifier: Intended Audience :: Developers
Classifier: License :: OSI Approved :: MIT License
Classifier: Natural Language :: English
Classifier: Operating System :: OS Independent
Classifier: Programming Language :: Python :: 3
Classifier: Programming Language :: Python :: 3 :: Only
Classifier: Programming Language :: Python :: 3.6
Classifier: Programming Language :: Python :: 3.7
Classifier: Programming Language :: Python :: 3.8
Classifier: Programming Language :: Python :: 3.9
Classifier: Programming Language :: Python :: 3.10
Classifier: Topic :: Internet
Requires-Python: >=3.6
License-File: LICENSE
Requires-Dist: requests
Requires-Dist: typing-extensions ; python_version < "3.8"
